README.rst
setup.cfg
setup.py
pyneat/__init__.py
pyneat/core.py
pyneat.egg-info/PKG-INFO
pyneat.egg-info/SOURCES.txt
pyneat.egg-info/dependency_links.txt
pyneat.egg-info/not-zip-safe
pyneat.egg-info/requires.txt
pyneat.egg-info/top_level.txt